beepbeep/__init__.py
beepbeep/bq.py
beepbeep/fb.py
beepbeep/gcs.py
beepbeep/ps.py
beepbeep/sm.py
beepbeep/ss.py
beepbeep/utilities.py
beepbeep-0.0.2.dist-info/METADATA
beepbeep-0.0.2.dist-info/WHEEL
beepbeep-0.0.2.dist-info/top_level.txt
beepbeep-0.0.2.dist-info/RECORD
